ahpri/__init__.py
ahpri/calcri.py
ahpri-2024.0.1.dist-info/METADATA
ahpri-2024.0.1.dist-info/WHEEL
ahpri-2024.0.1.dist-info/licenses/LICENSE
ahpri-2024.0.1.dist-info/RECORD
