Metadata-Version: 2.3
Name: ahpri
Version: 2024.0.1
Summary: Calculate AHP Random Index from dataset
Author-email: Andreas Schulz <andreas.schulz@smexibel.de>
License: MIT License
License-File: LICENSE
Keywords: ahpri,python
Classifier: Development Status :: 3 - Alpha
Classifier: Intended Audience :: Science/Research
Classifier: License :: OSI Approved :: MIT License
Classifier: Operating System :: OS Independent
Classifier: Programming Language :: Python :: 3
Classifier: Topic :: Scientific/Engineering :: Information Analysis
Requires-Python: >=3.10
